masp/__init__.py
masp/utils.py
masp/validate_data_types.py
masp/version.py
masp/array_response_simulator/__init__.py
masp/array_response_simulator/modal_coefs.py
masp/array_response_simulator/scatter.py
masp/array_response_simulator/simulate_array.py
masp/array_response_simulator/sph_functions.py
masp/shoebox_room_sim/__init__.py
masp/shoebox_room_sim/absorption_module.py
masp/shoebox_room_sim/acoustics.py
masp/shoebox_room_sim/apply_source_signals.py
masp/shoebox_room_sim/compute_echograms.py
masp/shoebox_room_sim/echogram.py
masp/shoebox_room_sim/image_source_method.py
masp/shoebox_room_sim/quantise.py
masp/shoebox_room_sim/rec_module.py
masp/shoebox_room_sim/render_rirs.py
masp/spherical_array_processing/__init__.py
masp/spherical_array_processing/array_sht_filters.py
masp/spherical_array_processing/evaluate_sht_filters.py
masp/spherical_array_processing/plot_functions.py
masp/spherical_array_processing/sph_array_characteristics.py
masp-0.1.0.dist-info/LICENSE.md
masp-0.1.0.dist-info/METADATA
masp-0.1.0.dist-info/WHEEL
masp-0.1.0.dist-info/top_level.txt
masp-0.1.0.dist-info/RECORD
