Metadata-Version: 2.1
Name: masp
Version: 0.1.0
Summary: Multichannel Acoustic Signal Processing
Home-page: https://github.com/andresperezlopez/masp
Author: Andres Perez-Lopez
Author-email: contact@andresperezlopez.com
License: UNKNOWN
Platform: UNKNOWN
Classifier: Programming Language :: Python :: 3
Classifier: License :: OSI Approved :: BSD License
Classifier: Operating System :: OS Independent
Requires-Python: >=3.6
